{
  "basic_info": {
    "symbol": "RBLX",
    "name": "Roblox\u00a0Corp",
    "sector": "TECHNOLOGY",
    "industry": "SERVICES-PREPACKAGED SOFTWARE",
    "country": "USA",
    "currency": "USD"
  },
  "market_data": {
    "market_cap": "86676668000",
    "shares_outstanding": "645033000",
    "52_week_high": "150.59",
    "52_week_low": "35.3",
    "50_day_ma": "104.22",
    "200_day_ma": "70.69"
  },
  "valuation_ratios": {
    "pe_ratio": "None",
    "peg_ratio": "8.18",
    "price_to_book": "245.39",
    "price_to_sales": "21.55",
    "ev_revenue": "21.34",
    "ev_ebitda": "-24.79"
  },
  "profitability_metrics": {
    "profit_margin": "-0.237",
    "operating_margin_ttm": "-0.298",
    "return_on_assets_ttm": "-0.0945",
    "return_on_equity_ttm": "-4.266",
    "gross_profit_ttm": "1076031000"
  },
  "financial_strength": {
    "revenue_ttm": "4023020000",
    "revenue_per_share_ttm": "6.03",
    "quarterly_revenue_growth": "0.209",
    "quarterly_earnings_growth": "0",
    "book_value": "0.51",
    "diluted_eps_ttm": "-1.43"
  },
  "dividend_info": {
    "dividend_per_share": "None",
    "dividend_yield": "None",
    "dividend_date": "None",
    "ex_dividend_date": "None"
  },
  "technical_indicators": {
    "beta": "1.608",
    "analyst_target_price": "139.45",
    "trailing_pe": "-",
    "forward_pe": "192.31"
  }
}